[
  {
    "full_name": "nodejs/node",
    "stargazers_count": 116660,
    "open_issues_count": 2601,
    "forks_count": 35308
  },
  {
    "full_name": "rust-lang/rust",
    "stargazers_count": 111884,
    "open_issues_count": 12323,
    "forks_count": 14733
  },
  {
    "full_name": "lcy101u/twitter-api-2020",
    "stargazers_count": 0,
    "open_issues_count": 0,
    "forks_count": 1
  },
  {
    "full_name": "MunGell/awesome-for-beginners",
    "stargazers_count": 84417,
    "open_issues_count": 91,
    "forks_count": 7826
  }
]