[
  {
    "full_name": "nodejs/node",
    "stargazers_count": 93824,
    "open_issues_count": 1707,
    "forks_count": 25414
  },
  {
    "full_name": "rust-lang/rust",
    "stargazers_count": 78705,
    "open_issues_count": 9576,
    "forks_count": 10480
  },
  {
    "full_name": "lcy101u/twitter-api-2020",
    "stargazers_count": 0,
    "open_issues_count": 0,
    "forks_count": 1
  },
  {
    "full_name": "MunGell/awesome-for-beginners",
    "stargazers_count": 49066,
    "open_issues_count": 80,
    "forks_count": 6128
  }
]