[
  {
    "full_name": "ncitron/badcrypto",
    "stargazers_count": 168,
    "open_issues_count": 0,
    "forks_count": 4
  },
  {
    "full_name": "lynchjames/obsidian-day-planner",
    "stargazers_count": 1194,
    "open_issues_count": 133,
    "forks_count": 423
  },
  {
    "full_name": "usememos/memos",
    "stargazers_count": 5642,
    "open_issues_count": 77,
    "forks_count": 331
  },
  {
    "full_name": "scaffold-eth/scaffold-eth",
    "stargazers_count": 8373,
    "open_issues_count": 51,
    "forks_count": 2974
  },
  {
    "full_name": "alacritty/alacritty",
    "stargazers_count": 44321,
    "open_issues_count": 326,
    "forks_count": 2640
  },
  {
    "full_name": "blueedgetechno/win11React",
    "stargazers_count": 7031,
    "open_issues_count": 21,
    "forks_count": 492
  },
  {
    "full_name": "locomotivemtl/locomotive-scroll",
    "stargazers_count": 6024,
    "open_issues_count": 225,
    "forks_count": 1021
  },
  {
    "full_name": "foolstack-omg/solidity-contracts",
    "stargazers_count": 31,
    "open_issues_count": 0,
    "forks_count": 9
  },
  {
    "full_name": "markmap/markmap",
    "stargazers_count": 4538,
    "open_issues_count": 49,
    "forks_count": 258
  },
  {
    "full_name": "colinhacks/zod",
    "stargazers_count": 17992,
    "open_issues_count": 144,
    "forks_count": 604
  },
  {
    "full_name": "google/googletest",
    "stargazers_count": 28896,
    "open_issues_count": 287,
    "forks_count": 9059
  },
  {
    "full_name": "DefiLlama/chainlist",
    "stargazers_count": 846,
    "open_issues_count": 9,
    "forks_count": 681
  },
  {
    "full_name": "novuhq/novu",
    "stargazers_count": 18120,
    "open_issues_count": 181,
    "forks_count": 1121
  },
  {
    "full_name": "AykutSarac/jsoncrack.com",
    "stargazers_count": 21640,
    "open_issues_count": 45,
    "forks_count": 1093
  },
  {
    "full_name": "extrawurst/gitui",
    "stargazers_count": 12093,
    "open_issues_count": 123,
    "forks_count": 380
  },
  {
    "full_name": "t4sk/sol-best-practices",
    "stargazers_count": 27,
    "open_issues_count": 0,
    "forks_count": 1
  },
  {
    "full_name": "spearbit/portfolio",
    "stargazers_count": 215,
    "open_issues_count": 2,
    "forks_count": 17
  },
  {
    "full_name": "diem/diem",
    "stargazers_count": 16704,
    "open_issues_count": 382,
    "forks_count": 2596
  },
  {
    "full_name": "tc39/ecma262",
    "stargazers_count": 13883,
    "open_issues_count": 391,
    "forks_count": 1291
  },
  {
    "full_name": "PrismJS/prism",
    "stargazers_count": 10973,
    "open_issues_count": 272,
    "forks_count": 1263
  },
  {
    "full_name": "KULeuven-COSIC/Starlink-FI",
    "stargazers_count": 811,
    "open_issues_count": 2,
    "forks_count": 105
  },
  {
    "full_name": "coder/coder",
    "stargazers_count": 3409,
    "open_issues_count": 276,
    "forks_count": 239
  },
  {
    "full_name": "openreplay/openreplay",
    "stargazers_count": 6821,
    "open_issues_count": 58,
    "forks_count": 318
  },
  {
    "full_name": "WTFAcademy/WTF-Ethers",
    "stargazers_count": 1134,
    "open_issues_count": 0,
    "forks_count": 163
  },
  {
    "full_name": "tauri-apps/tauri",
    "stargazers_count": 58036,
    "open_issues_count": 352,
    "forks_count": 1525
  },
  {
    "full_name": "honzaap/GithubCity",
    "stargazers_count": 951,
    "open_issues_count": 1,
    "forks_count": 45
  },
  {
    "full_name": "stakewithus/defi-by-example",
    "stargazers_count": 444,
    "open_issues_count": 8,
    "forks_count": 188
  },
  {
    "full_name": "oven-sh/bun",
    "stargazers_count": 38394,
    "open_issues_count": 501,
    "forks_count": 942
  },
  {
    "full_name": "lcy101u/file-sharing-encrypt",
    "stargazers_count": 1,
    "open_issues_count": 0,
    "forks_count": 0
  },
  {
    "full_name": "denoland/fresh",
    "stargazers_count": 9875,
    "open_issues_count": 165,
    "forks_count": 415
  }
]