[
  {
    "full_name": "alacritty/alacritty",
    "stargazers_count": 42996,
    "open_issues_count": 323,
    "forks_count": 2542
  },
  {
    "full_name": "blueedgetechno/win11React",
    "stargazers_count": 6706,
    "open_issues_count": 21,
    "forks_count": 423
  },
  {
    "full_name": "locomotivemtl/locomotive-scroll",
    "stargazers_count": 5781,
    "open_issues_count": 215,
    "forks_count": 971
  },
  {
    "full_name": "foolstack-omg/solidity-contracts",
    "stargazers_count": 30,
    "open_issues_count": 0,
    "forks_count": 8
  },
  {
    "full_name": "markmap/markmap",
    "stargazers_count": 4211,
    "open_issues_count": 46,
    "forks_count": 243
  },
  {
    "full_name": "colinhacks/zod",
    "stargazers_count": 13532,
    "open_issues_count": 117,
    "forks_count": 486
  },
  {
    "full_name": "google/googletest",
    "stargazers_count": 28386,
    "open_issues_count": 278,
    "forks_count": 8941
  },
  {
    "full_name": "DefiLlama/chainlist",
    "stargazers_count": 680,
    "open_issues_count": 6,
    "forks_count": 549
  },
  {
    "full_name": "novuhq/novu",
    "stargazers_count": 12497,
    "open_issues_count": 147,
    "forks_count": 787
  },
  {
    "full_name": "AykutSarac/jsoncrack.com",
    "stargazers_count": 19143,
    "open_issues_count": 34,
    "forks_count": 929
  },
  {
    "full_name": "extrawurst/gitui",
    "stargazers_count": 11332,
    "open_issues_count": 106,
    "forks_count": 350
  },
  {
    "full_name": "t4sk/sol-best-practices",
    "stargazers_count": 27,
    "open_issues_count": 0,
    "forks_count": 1
  },
  {
    "full_name": "spearbit/portfolio",
    "stargazers_count": 128,
    "open_issues_count": 0,
    "forks_count": 12
  },
  {
    "full_name": "diem/diem",
    "stargazers_count": 16669,
    "open_issues_count": 383,
    "forks_count": 2589
  },
  {
    "full_name": "tc39/ecma262",
    "stargazers_count": 13730,
    "open_issues_count": 389,
    "forks_count": 1275
  },
  {
    "full_name": "PrismJS/prism",
    "stargazers_count": 10775,
    "open_issues_count": 241,
    "forks_count": 1250
  },
  {
    "full_name": "KULeuven-COSIC/Starlink-FI",
    "stargazers_count": 715,
    "open_issues_count": 2,
    "forks_count": 94
  },
  {
    "full_name": "coder/coder",
    "stargazers_count": 2672,
    "open_issues_count": 280,
    "forks_count": 178
  },
  {
    "full_name": "openreplay/openreplay",
    "stargazers_count": 6269,
    "open_issues_count": 72,
    "forks_count": 288
  },
  {
    "full_name": "WTFAcademy/WTF-Ethers",
    "stargazers_count": 788,
    "open_issues_count": 2,
    "forks_count": 110
  },
  {
    "full_name": "tauri-apps/tauri",
    "stargazers_count": 54084,
    "open_issues_count": 278,
    "forks_count": 1393
  },
  {
    "full_name": "honzaap/GithubCity",
    "stargazers_count": 901,
    "open_issues_count": 1,
    "forks_count": 39
  },
  {
    "full_name": "stakewithus/defi-by-example",
    "stargazers_count": 408,
    "open_issues_count": 8,
    "forks_count": 173
  },
  {
    "full_name": "oven-sh/bun",
    "stargazers_count": 36042,
    "open_issues_count": 392,
    "forks_count": 854
  },
  {
    "full_name": "lcy101u/file-sharing-encrypt",
    "stargazers_count": 1,
    "open_issues_count": 0,
    "forks_count": 0
  },
  {
    "full_name": "denoland/fresh",
    "stargazers_count": 9424,
    "open_issues_count": 148,
    "forks_count": 375
  },
  {
    "full_name": "SunWeb3Sec/DeFiHackLabs",
    "stargazers_count": 1523,
    "open_issues_count": 0,
    "forks_count": 261
  },
  {
    "full_name": "SunWeb3Sec/DeFiVulnLabs",
    "stargazers_count": 518,
    "open_issues_count": 0,
    "forks_count": 73
  },
  {
    "full_name": "preactjs/preact",
    "stargazers_count": 33302,
    "open_issues_count": 223,
    "forks_count": 1833
  },
  {
    "full_name": "InfuriousICC/Google-Dorks-Simplified",
    "stargazers_count": 172,
    "open_issues_count": 0,
    "forks_count": 25
  }
]